gja.py
gja-0.3.dist-info/LICENSE
gja-0.3.dist-info/METADATA
gja-0.3.dist-info/WHEEL
gja-0.3.dist-info/top_level.txt
gja-0.3.dist-info/RECORD
