Metadata-Version: 2.1
Name: gja
Version: 0.3
Summary: Gauss-Jordan assistant
Home-page: https://github.com/aroberge/gauss-jordan-assistant
Author: André Roberge
Author-email: Andre.Roberge@gmail.com
License: UNKNOWN
Platform: UNKNOWN
Classifier: Development Status :: 1 - Planning
Classifier: License :: OSI Approved :: MIT License
Classifier: Programming Language :: Python :: 3
Classifier: Programming Language :: Python :: 3.8
Requires-Python: >=3.8
Requires-Dist: rich
